{"title":"Boss Savana orders Auntie Trisha","photos":[{"url":"https://www.pornhub.com/photo/834004211","views":"281","rating":"100%","preview":"https://ei.phncdn.com/pics/albums/075/941/081/834004211/(m=eiJ_8f)(mh=_e5qRePbgODrk010)original_834004211.jpg"},{"url":"https://www.pornhub.com/photo/834004201","views":"290","rating":"0%","preview":"https://ei.phncdn.com/pics/albums/075/941/081/834004201/(m=eiJ_8f)(mh=tPd8xc5HeTBz4EVq)original_834004201.jpg"},{"url":"https://www.pornhub.com/photo/834004231","views":"265","rating":"100%","preview":"https://ei.phncdn.com/pics/albums/075/941/081/834004231/(m=eiJ_8f)(mh=fpQpWtMft_3sCtom)original_834004231.jpg"},{"url":"https://www.pornhub.com/photo/834004281","views":"244","rating":"0%","preview":"https://ei.phncdn.com/pics/albums/075/941/081/834004281/(m=eiJ_8f)(mh=VSR0ub41kIn_2cim)original_834004281.jpg"},{"url":"https://www.pornhub.com/photo/834004321","views":"274","rating":"100%","preview":"https://ei.phncdn.com/pics/albums/075/941/081/834004321/(m=eiJ_8f)(mh=5NhpVym4mY5izfMZ)original_834004321.jpg"},{"url":"https://www.pornhub.com/photo/834004261","views":"322","rating":"100%","preview":"https://ei.phncdn.com/pics/albums/075/941/081/834004261/(m=eiJ_8f)(mh=mqn7jIs9-vhaCHbY)original_834004261.jpg"},{"url":"https://www.pornhub.com/photo/834004251","views":"250","rating":"0%","preview":"https://ei.phncdn.com/pics/albums/075/941/081/834004251/(m=eiJ_8f)(mh=50pSLL2lCC9ieHJQ)original_834004251.jpg"},{"url":"https://www.pornhub.com/photo/834004241","views":"229","rating":"0%","preview":"https://ei.phncdn.com/pics/albums/075/941/081/834004241/(m=eiJ_8f)(mh=c_WCkJV-A-h3qA4t)original_834004241.jpg"},{"url":"https://www.pornhub.com/photo/834004301","views":"225","rating":"100%","preview":"https://ei.phncdn.com/pics/albums/075/941/081/834004301/(m=eiJ_8f)(mh=5O5wIE3dIz0Mp5A1)original_834004301.jpg"},{"url":"https://www.pornhub.com/photo/834004291","views":"283","rating":"100%","preview":"https://ei.phncdn.com/pics/albums/075/941/081/834004291/(m=eiJ_8f)(mh=2c0bqay8XGgpn_8c)original_834004291.jpg"},{"url":"https://www.pornhub.com/photo/834004191","views":"760","rating":"100%","preview":"https://ei.phncdn.com/pics/albums/075/941/081/834004191/(m=eiJ_8f)(mh=PlnBZSh07Q_kzAas)original_834004191.jpg"},{"url":"https://www.pornhub.com/photo/834004221","views":"526","rating":"100%","preview":"https://ei.phncdn.com/pics/albums/075/941/081/834004221/(m=eiJ_8f)(mh=FwMS0UTfrYQ8ZE61)original_834004221.jpg"},{"url":"https://www.pornhub.com/photo/834004331","views":"311","rating":"100%","preview":"https://ei.phncdn.com/pics/albums/075/941/081/834004331/(m=eiJ_8f)(mh=5WNTdPF9L3PSOelN)original_834004331.jpg"},{"url":"https://www.pornhub.com/photo/834004271","views":"460","rating":"100%","preview":"https://ei.phncdn.com/pics/albums/075/941/081/834004271/(m=eiJ_8f)(mh=KToUq8PqnMPQ7O9B)original_834004271.jpg"},{"url":"https://www.pornhub.com/photo/834004311","views":"239","rating":"0%","preview":"https://ei.phncdn.com/pics/albums/075/941/081/834004311/(m=eiJ_8f)(mh=sUjfh38g9zbDHn3k)original_834004311.jpg"}],"provider":{"id":2752380,"username":"OldNanny","url":"/users/oldnanny"},"tags":["mature","old and young","bbw","pussy","big dick","masturbation","big boobs","big cock"]}