{"data":[{"name":"Sugarsweet099","url":"https://www.pornhub.com/model/sugarsweet099","views":"41.8K","videoNum":10,"rank":27286,"photo":"https://ei.phncdn.com/(m=bLazqgKlbyaT)(mh=y3IRiLxXYEp63Y5i)3ad3eb72-de46-4047-b757-6e7717e43e2e.jpg","verified":true,"awarded":false},{"name":"MitzDitzyKitty","url":"https://www.pornhub.com/model/mitzditzykitty","views":"164K","videoNum":17,"rank":27287,"photo":"https://ei.phncdn.com/(m=bLazqgKlbyaT)(mh=5RZFtzOt7FBhgbKg)9670316c-6aa5-4e3f-9bd0-de73b811ca85.jpg","verified":true,"awarded":false},{"name":"LunaWhiteXX","url":"https://www.pornhub.com/model/lunawhitexx","views":"73.7K","videoNum":6,"rank":27289,"photo":"https://ei.phncdn.com/(m=bLazqgKlbyaT)(mh=3kmBHFD8e8ZBD4ze)ded67212-811b-4819-96ee-94b8aacc31fd.jpg","verified":true,"awarded":false},{"name":"SweetCandyHina","url":"https://www.pornhub.com/model/sweetcandyhina","views":"329K","videoNum":5,"rank":27290,"photo":"https://ei.phncdn.com/(m=bLazqgKlbyaT)(mh=EKM7C5OQ139I3vZz)77c85513-16f9-41ed-9fdd-9b1e40be63c9.jpg","verified":true,"awarded":false},{"name":"Deanna Deadly","url":"https://www.pornhub.com/model/deanna-deadly","views":"117K","videoNum":16,"rank":27291,"photo":"https://ei.phncdn.com/pics/users/395/002/632/avatar1596298289/(m=eidYGCjadOf)(mh=TNUz74W0EX_3Nvb3)200x200.jpg","verified":true,"awarded":false},{"name":"manami_MensEsthe","url":"https://www.pornhub.com/model/manami_mensesthe","views":"4.2M","videoNum":45,"rank":27293,"photo":"https://ei.phncdn.com/pics/users/u/002/209/512/981/avatar1633245404/(m=eidYGCjadOf)(mh=q0r1-hKP3BcANLT6)200x200.jpg","verified":true,"awarded":false},{"name":"Holy_pepper","url":"https://www.pornhub.com/model/holy_pepper","views":"1.5M","videoNum":64,"rank":27294,"photo":"https://ei.phncdn.com/(m=bLazqgKlbyaT)(mh=4jd_ksDx72yqEAmq)e1f26206-4bcb-4590-a6b4-81ba14644114.jpg","verified":true,"awarded":false},{"name":"cinnabum","url":"https://www.pornhub.com/model/cinnabum","views":"894K","videoNum":22,"rank":27297,"photo":"https://ei.phncdn.com/pics/users/699/754/401/avatar1570808334/(m=eidYGCjadOf)(mh=CfFPvJK2SfqX5alT)200x200.jpg","verified":true,"awarded":false},{"name":"boomsar","url":"https://www.pornhub.com/model/boomsar","views":"18.2K","videoNum":3,"rank":27298,"photo":"https://ei.phncdn.com/(m=bLazqgKlbyaT)(mh=KtBq9V9v6rsp9I1V)600df835-638a-427d-a442-cee4c28dc5b2.jpg","verified":true,"awarded":false},{"name":"LatinaTrip","url":"https://www.pornhub.com/model/latinatrip","views":"550K","videoNum":51,"rank":27299,"photo":"https://ei.phncdn.com/(m=bLazqgKlbyaT)(mh=BuIyOok_2PlDf9OA)7e146609-ea83-4888-9a89-7453bd04f516.jpg","verified":true,"awarded":false},{"name":"Cecee Superhead","url":"https://www.pornhub.com/model/cecee-superhead","views":"1.2M","videoNum":42,"rank":27300,"photo":"https://ei.phncdn.com/pics/users/066/910/681/avatar1540087794/(m=eidYGCjadOf)(mh=Ri2bHEAgxASSgUYl)200x200.jpg","verified":true,"awarded":false},{"name":"Miss Tisa","url":"https://www.pornhub.com/model/miss-tisa","views":"487K","videoNum":5,"rank":27301,"photo":"https://ei.phncdn.com/(m=bLazqgKlbyaT)(mh=LkV8eT8pZkIeojq_)596f6cef-2693-4a14-b204-72b0d062751c.jpg","verified":true,"awarded":false},{"name":"RealNikkiGrey","url":"https://www.pornhub.com/model/realnikkigrey","views":"535K","videoNum":13,"rank":27302,"photo":"https://ei.phncdn.com/(m=eidYGCjadOf)(mh=V1u-BLQ0uSHnIWg9)eb2d936a-c44b-4292-9a6f-62f609d0e24d.jpg","verified":true,"awarded":false},{"name":"Dulce Zorrita","url":"https://www.pornhub.com/model/dulce-zorrita","views":"679K","videoNum":16,"rank":27303,"photo":"https://ei.phncdn.com/pics/users/u/001/197/254/692/avatar1586380575/(m=eidYGCjadOf)(mh=LYdORZW_jGd-fVCD)200x200.jpg","verified":true,"awarded":false},{"name":"kimmiemymo","url":"https://www.pornhub.com/model/kimmiemymo","views":"3.6M","videoNum":22,"rank":27304,"photo":"https://ei.phncdn.com/pics/users/u/001/800/785/432/avatar1619792738/(m=eidYGCjadOf)(mh=FPEO8t7C39gRLuN4)200x200.jpg","verified":true,"awarded":false},{"name":"ShyandRaw","url":"https://www.pornhub.com/model/shyandraw","views":"16.8K","videoNum":7,"rank":27305,"photo":"https://ei.phncdn.com/(m=bLazqgKlbyaT)(mh=d4bs39uBy2E8W_Lx)f85af561-ad9b-4b45-9f33-2c7131a0c6be.jpg","verified":true,"awarded":false},{"name":"Ivyrose12345","url":"https://www.pornhub.com/model/ivyrose12345","views":"787K","videoNum":26,"rank":27306,"photo":"https://ei.phncdn.com/pics/users/u/002/239/331/591/avatar1635297908/(m=eidYGCjadOf)(mh=IOfO-M0zToNYZOE7)200x200.jpg","verified":true,"awarded":false},{"name":"MoshiiAG","url":"https://www.pornhub.com/model/moshiiag","views":"251K","videoNum":6,"rank":27307,"photo":"https://ei.phncdn.com/(m=bLazqgKlbyaT)(mh=B70zOgS9KzKMHsQT)d58cf9ba-9d5a-4b43-9605-a4a2024541a9.jpg","verified":true,"awarded":false},{"name":"Trapcunebony","url":"https://www.pornhub.com/model/trapcunebony","views":"2.1K","videoNum":1,"rank":27309,"photo":"https://ei.phncdn.com/(m=bLazqgKlbyaT)(mh=do30mk49_2W__un0)e5b945ac-a204-430b-82d7-29b0c76a3242.jpg","verified":true,"awarded":false},{"name":"HongKongCandy","url":"https://www.pornhub.com/model/hongkongcandy","views":"14.7K","videoNum":5,"rank":27310,"photo":"https://ei.phncdn.com/(m=bLazqgKlbyaT)(mh=igbqWPj0pTaApMow)a62c7fbe-79a7-45b5-b241-464e70c06c06.jpg","verified":true,"awarded":false},{"name":"Ember Ann","url":"https://www.pornhub.com/model/ember-ann","views":"60K","videoNum":4,"rank":27312,"photo":"https://ei.phncdn.com/(m=bLazqgKlbyaT)(mh=KoeOWFadZuWpYTnO)689483c7-57cf-466c-95a6-df5403385f33.jpg","verified":true,"awarded":false},{"name":"Vanesweett","url":"https://www.pornhub.com/model/vanesweett","views":"346K","videoNum":21,"rank":27314,"photo":"https://ei.phncdn.com/pics/users/u/001/429/573/491/avatar1585228502/(m=eidYGCjadOf)(mh=dh2p-2MwdA7YLWwS)200x200.jpg","verified":true,"awarded":false},{"name":"Kandyshortarse","url":"https://www.pornhub.com/model/kandyshortarse","views":"256K","videoNum":35,"rank":27318,"photo":"https://ei.phncdn.com/(m=bLazqgKlbyaT)(mh=1cviQAgbcggIqoIe)3c7f9314-f364-426f-8c18-8fa5a02e4f46.jpg","verified":true,"awarded":false},{"name":"Peachyy Bootyy","url":"https://www.pornhub.com/model/peachyy-bootyy","views":"1.2M","videoNum":30,"rank":27320,"photo":"https://ei.phncdn.com/pics/users/u/001/649/234/802/avatar1636187634/(m=eidYGCjadOf)(mh=07Q3A6rVqOkbNgqw)200x200.jpg","verified":true,"awarded":false},{"name":"LukeOrtiz","url":"https://www.pornhub.com/model/lukeortiz","views":"589K","videoNum":13,"rank":27322,"photo":"https://ei.phncdn.com/(m=bLazqgKlbyaT)(mh=2qwox2I0WGWAhu8W)48034f99-b301-4c81-943c-aee2b609a00e.jpg","verified":true,"awarded":false},{"name":"Rogerio Cg","url":"https://www.pornhub.com/model/rogerio-cg","views":"486K","videoNum":52,"rank":27323,"photo":"https://ei.phncdn.com/(m=eidYGCjadOf)(mh=GKbeq4Ch8dqnYPwL)261e5758-0aad-4dd8-9b7f-f909a03029d9.jpg","verified":true,"awarded":false},{"name":"Cristalclocks1","url":"https://www.pornhub.com/model/cristalclocks1","views":"25.3K","videoNum":26,"rank":27324,"photo":"https://ei.phncdn.com/(m=bLazqgKlbyaT)(mh=kiKND2t0UBBLhELF)be3e90c8-2bef-4899-b2d7-801e96a6c604.jpg","verified":true,"awarded":false},{"name":"Barbie Bunny","url":"https://www.pornhub.com/model/barbie-bunny","views":"47K","videoNum":5,"rank":27325,"photo":"https://ei.phncdn.com/pics/users/620/781/081/avatar1537755721/(m=eidYGCjadOf)(mh=PH4Iu7oKn-XPSnWa)200x200.jpg","verified":true,"awarded":false},{"name":"prettykitty6090","url":"https://www.pornhub.com/model/prettykitty6090","views":"236K","videoNum":4,"rank":27327,"photo":"https://ei.phncdn.com/(m=bLazqgKlbyaT)(mh=u-8NeJiK_6xMl_8g)aca759e5-c2da-445e-afb2-6fd44469c99f.jpg","verified":true,"awarded":false},{"name":"EbonyPrincessKayKay","url":"https://www.pornhub.com/model/ebonyprincesskaykay","views":"215K","videoNum":21,"rank":27329,"photo":"https://ei.phncdn.com/(m=bLazqgKlbyaT)(mh=2O_rL-NVB5c504Zt)7df48aef-fc12-40f2-8850-bad3ae82a13f.jpg","verified":true,"awarded":false},{"name":"1GreenSweater","url":"https://www.pornhub.com/model/1greensweater","views":"147K","videoNum":47,"rank":27330,"photo":"https://ei.phncdn.com/pics/users/default/pornhub/(m=bJazqgKlbyaT)(mh=edkXMLCC_MjmYEiZ)male.jpg","verified":true,"awarded":false},{"name":"JessebelleLuv","url":"https://www.pornhub.com/model/jessebelleluv","views":"387K","videoNum":11,"rank":27333,"photo":"https://ei.phncdn.com/pics/users/437/464/432/avatar1550850115/(m=eidYGCjadOf)(mh=aVgO9rirBhpENkd6)200x200.jpg","verified":true,"awarded":false},{"name":"Gesy66","url":"https://www.pornhub.com/model/gesy66","views":"71.9K","videoNum":23,"rank":27334,"photo":"https://ei.phncdn.com/(m=bLazqgKlbyaT)(mh=LwOAGAwCscjj3RuR)0c6c101a-4eec-4bbf-baef-06cab8527180.jpg","verified":true,"awarded":false},{"name":"Hazel The Housewife","url":"https://www.pornhub.com/model/hazel-the-housewife","views":"940K","videoNum":9,"rank":27335,"photo":"https://ei.phncdn.com/pics/users/u/001/933/321/392/avatar1602268625/(m=eidYGCjadOf)(mh=gXL9kf-Rhzbushij)200x200.jpg","verified":true,"awarded":false},{"name":"hardfortiny9296","url":"https://www.pornhub.com/model/hardfortiny9296","views":"283K","videoNum":19,"rank":27337,"photo":"https://ei.phncdn.com/(m=eidYGCjadOf)(mh=sIYNm4OIPdoFJCMi)4cc9373b-0e1b-4f20-afcb-3e650fa3f2cb.jpg","verified":true,"awarded":false},{"name":"Stormeesmilesxxx","url":"https://www.pornhub.com/model/stormeesmilesxxx","views":"312K","videoNum":30,"rank":27339,"photo":"https://ei.phncdn.com/(m=eidYGCjadOf)(mh=Myk9e7ufTLHyZPon)a027fa0d-eeee-402d-ad8c-b37bf250ac56.jpg","verified":true,"awarded":false},{"name":"Sweetblondiee","url":"https://www.pornhub.com/model/sweetblondiee","views":"192K","videoNum":48,"rank":27340,"photo":"https://ei.phncdn.com/(m=bLazqgKlbyaT)(mh=Fy293YADtpjYaSLJ)fab91433-4f8f-4b11-bda8-af7902a70619.jpg","verified":true,"awarded":false},{"name":"SweetDaleLee","url":"https://www.pornhub.com/model/sweetdalelee","views":"544K","videoNum":20,"rank":27341,"photo":"https://ei.phncdn.com/pics/users/u/001/124/501/001/avatar1583283652/(m=eidYGCjadOf)(mh=-bi70VJ7uZvt_7wW)200x200.jpg","verified":true,"awarded":false},{"name":"Mura Suru","url":"https://www.pornhub.com/model/mura-suru","views":"91.6K","videoNum":5,"rank":27343,"photo":"https://ei.phncdn.com/(m=bLazqgKlbyaT)(mh=1Eawl7EiFh7XitJP)2205db6a-83e1-4aed-bc3d-4b80c4fc677f.jpg","verified":true,"awarded":false},{"name":"Sofi Vega Official","url":"https://www.pornhub.com/pornstar/sofi-vega-official","views":"648K","videoNum":20,"rank":27344,"photo":"https://ei.phncdn.com/(m=bLqDuhKlbyaT)(mh=QHrYub4KSHt_R0Sl)d8f68576-cb38-4a06-8a1b-3bcf3f96d550.jpg","verified":true,"awarded":false},{"name":"Milf Mallori","url":"https://www.pornhub.com/model/milf-mallori","views":"239K","videoNum":31,"rank":27346,"photo":"https://ei.phncdn.com/pics/users/u/002/113/206/341/avatar1619187737/(m=eidYGCjadOf)(mh=uO-QgSeNopSXqt7I)200x200.jpg","verified":true,"awarded":false},{"name":"SensualDuo134","url":"https://www.pornhub.com/model/sensualduo134","views":"515K","videoNum":23,"rank":27347,"photo":"https://ei.phncdn.com/(m=eidYGCjadOf)(mh=55Hk6gDHoZYUqX2p)d2c7ca63-e902-4072-a72b-d5de88a10125.jpg","verified":true,"awarded":false},{"name":"Ruby Labelle","url":"https://www.pornhub.com/model/ruby-labelle","views":"96.4K","videoNum":20,"rank":27348,"photo":"https://ei.phncdn.com/(m=bLazqgKlbyaT)(mh=hPTLaXPbzEu1c4Ar)9e0ec106-0a8f-4b47-9604-367033b7b68f.jpg","verified":true,"awarded":false},{"name":"Crazy_easy","url":"https://www.pornhub.com/model/crazy_easy","views":"353K","videoNum":90,"rank":27349,"photo":"https://ei.phncdn.com/(m=bLazqgKlbyaT)(mh=xzBsqFHYjoyKuJPg)ea2311be-00c1-4599-8f29-0fd252f8e5bd.jpg","verified":true,"awarded":false},{"name":"Scarlett Rae","url":"https://www.pornhub.com/model/scarlett-rae","views":"2.8K","videoNum":2,"rank":27352,"photo":"https://ei.phncdn.com/pics/users/801/141/061/avatar1555043636/(m=eidYGCjadOf)(mh=1Ah-d2QP1lQdb0Ki)200x200.jpg","verified":true,"awarded":false},{"name":"Trinigatita","url":"https://www.pornhub.com/model/trinigatita","views":"3.3M","videoNum":20,"rank":27353,"photo":"https://ei.phncdn.com/(m=bLazqgKlbyaT)(mh=uGGVbNaxAJZImrPb)99c32c00-df3d-407f-ad1d-538df4300e5c.jpg","verified":true,"awarded":false},{"name":"Kate Divine","url":"https://www.pornhub.com/model/kate-divine","views":"35.3K","videoNum":10,"rank":27354,"photo":"https://ei.phncdn.com/(m=eidYGCjadOf)(mh=fd1CWe8ZY6t2lSlJ)0aa3b66b-3250-456a-abc5-d9426e465cbb.jpg","verified":true,"awarded":false},{"name":"IvyLieber","url":"https://www.pornhub.com/model/ivylieber","views":"47.5K","videoNum":13,"rank":27356,"photo":"https://ei.phncdn.com/(m=bLazqgKlbyaT)(mh=kAAKdBoNID1cKthF)6779250c-91e0-4583-b561-8fbd0db98e8e.jpg","verified":true,"awarded":false},{"name":"Dais0y","url":"https://www.pornhub.com/model/dais0y","views":"55.9K","videoNum":8,"rank":27359,"photo":"https://ei.phncdn.com/(m=bLazqgKlbyaT)(mh=hkZfUkCaZn_MdEAg)98200160-e8e0-4054-8e8f-6012a6769dc2.jpg","verified":true,"awarded":false},{"name":"Fantasy Chats","url":"https://www.pornhub.com/model/fantasy-chats","views":"1.4M","videoNum":136,"rank":27360,"photo":"https://ei.phncdn.com/pics/users/534/122/152/avatar1588524474/(m=eidYGCjadOf)(mh=zejuCi-fAKVMYd9L)200x200.jpg","verified":true,"awarded":false},{"name":"Kayla baby","url":"https://www.pornhub.com/model/kayla-baby","views":"53","videoNum":0,"rank":27361,"photo":"https://ei.phncdn.com/pics/users/u/001/633/912/022/avatar1587084150/(m=eidYGCjadOf)(mh=UoFM2cIcUoRpi3Tv)200x200.jpg","verified":true,"awarded":false},{"name":"Ruby Sex","url":"https://www.pornhub.com/model/ruby-sex","views":"47.8K","videoNum":16,"rank":27362,"photo":"https://ei.phncdn.com/pics/users/u/001/564/176/951/avatar1585777253/(m=eidYGCjadOf)(mh=TmapzQrb9ZLixcQH)200x200.jpg","verified":true,"awarded":false},{"name":"elourawild","url":"https://www.pornhub.com/model/elourawild","views":"31.5K","videoNum":3,"rank":27363,"photo":"https://ei.phncdn.com/(m=bLazqgKlbyaT)(mh=UkAfn8otsI38HcmH)f19e6746-2460-4460-9339-5ce9b74fef51.jpg","verified":true,"awarded":false},{"name":"Mei_Amai","url":"https://www.pornhub.com/model/mei_amai","views":"7.9M","videoNum":55,"rank":27365,"photo":"https://ei.phncdn.com/(m=bLazqgKlbyaT)(mh=l9aiM1oBx9V9A7L8)6b4d635c-f07c-4399-9996-68466d30e6ec.jpg","verified":true,"awarded":false},{"name":"June Starr","url":"https://www.pornhub.com/model/june-starr","views":"69.9K","videoNum":12,"rank":27367,"photo":"https://ei.phncdn.com/pics/users/915/088/771/avatar1564135042/(m=eidYGCjadOf)(mh=gTApoAxdBpZMB1Sg)200x200.jpg","verified":true,"awarded":false},{"name":"SmokeAndWine","url":"https://www.pornhub.com/model/smokeandwine","views":"2.8M","videoNum":28,"rank":27368,"photo":"https://ei.phncdn.com/pics/users/895/693/641/avatar1570138173/(m=eidYGCjadOf)(mh=2KeQMUYn-fZA5ftz)200x200.jpg","verified":true,"awarded":false},{"name":"Nymphos5000","url":"https://www.pornhub.com/model/nymphos5000","views":"744K","videoNum":18,"rank":27369,"photo":"https://ei.phncdn.com/pics/users/429/344/562/avatar1522339107/(m=eidYGCjadOf)(mh=biG2zQyEUXosfqsc)200x200.jpg","verified":true,"awarded":false},{"name":"LuxuryCouple555","url":"https://www.pornhub.com/model/luxurycouple555","views":"358K","videoNum":16,"rank":27369,"photo":"https://ei.phncdn.com/(m=eidYGCjadOf)(mh=08UWPQHlEPem7tvf)540dfbd0-69fc-463f-bf7b-7a9768a6f5b2.jpg","verified":true,"awarded":false},{"name":"Alyssa remi","url":"https://www.pornhub.com/model/alyssa-remi","views":"341K","videoNum":16,"rank":27370,"photo":"https://ei.phncdn.com/pics/users/u/002/140/883/861/avatar1623731770/(m=eidYGCjadOf)(mh=RzEpBzAJHUP9FyYE)200x200.jpg","verified":true,"awarded":false}],"paging":{"current":350,"maxPage":1358,"isEnd":false}}