{"title":"Sharon White and Elena Lux","photos":[{"url":"https://www.pornhub.com/photo/839056051","views":"1.3K","rating":"88%","preview":"https://ei.phncdn.com/(m=bJaz0NV)(mh=bZy7dKRXbrHoHvje)a2a0a8a2-b939-4cf5-a76a-9a3bba705064.jpg"},{"url":"https://www.pornhub.com/photo/839056121","views":"1.4K","rating":"100%","preview":"https://ei.phncdn.com/(m=bJaz0NV)(mh=1DU7WWA0c2qv0AZP)c912f656-3039-4f97-9f8f-65e544de4eeb.jpg"},{"url":"https://www.pornhub.com/photo/839056091","views":"1.3K","rating":"100%","preview":"https://ei.phncdn.com/(m=bJaz0NV)(mh=uw4-B0M0RW25ViuQ)ef27dd8f-ab36-4ab0-ae33-04bee15a7054.jpg"},{"url":"https://www.pornhub.com/photo/839056011","views":"1.6K","rating":"100%","preview":"https://ei.phncdn.com/(m=bJaz0NV)(mh=17TbSwZbwBlpp-w7)66a361ea-02b5-4182-af0e-092ab8353e73.jpg"},{"url":"https://www.pornhub.com/photo/839055981","views":"1.6K","rating":"100%","preview":"https://ei.phncdn.com/(m=bJaz0NV)(mh=3CA_w3nzL2TOvufz)4a113d26-d328-42fe-8a5d-53f8d2ed6abb.jpg"},{"url":"https://www.pornhub.com/photo/839056041","views":"1.2K","rating":"100%","preview":"https://ei.phncdn.com/(m=bJaz0NV)(mh=vyQTNNdFGn6nrgIj)da9a46e3-ba74-4807-83da-3fe83f3f815c.jpg"},{"url":"https://www.pornhub.com/photo/839056131","views":"1K","rating":"75%","preview":"https://ei.phncdn.com/(m=bJaz0NV)(mh=dEvPpjT-6Rj_wsWQ)6c3e24cc-e5f9-4d3a-8053-7dd365249f6b.jpg"},{"url":"https://www.pornhub.com/photo/839056071","views":"1.1K","rating":"100%","preview":"https://ei.phncdn.com/(m=bJaz0NV)(mh=rImCHY0OEbKeWxfE)26a3ebcb-9125-4ce1-b89f-7bdde3388047.jpg"},{"url":"https://www.pornhub.com/photo/839055971","views":"954","rating":"100%","preview":"https://ei.phncdn.com/(m=bJaz0NV)(mh=HSd7rGFYexFtPsxb)d5f40d8b-63bd-40a2-8223-f4a5644c703c.jpg"},{"url":"https://www.pornhub.com/photo/839056111","views":"1.4K","rating":"100%","preview":"https://ei.phncdn.com/(m=bJaz0NV)(mh=zEbjwbzknyIpZFWt)25eb629f-309b-4549-abfb-ee6a4961326f.jpg"},{"url":"https://www.pornhub.com/photo/839056031","views":"1.3K","rating":"100%","preview":"https://ei.phncdn.com/(m=bJaz0NV)(mh=SsMeyPREUXPmKNdz)73ada8b1-2f1b-46f9-a98c-72b00e048699.jpg"},{"url":"https://www.pornhub.com/photo/839056061","views":"867","rating":"67%","preview":"https://ei.phncdn.com/(m=bJaz0NV)(mh=rcXdNk_znh6pcetG)f1419c71-90dc-4ec4-8b17-743b1e1c95ed.jpg"},{"url":"https://www.pornhub.com/photo/839056081","views":"868","rating":"100%","preview":"https://ei.phncdn.com/(m=bJaz0NV)(mh=7kfIqqkDfS12ifRY)f7b48a2e-055b-4454-a5cf-c31a028c9a2c.jpg"},{"url":"https://www.pornhub.com/photo/839055941","views":"615","rating":"100%","preview":"https://ei.phncdn.com/(m=bJaz0NV)(mh=YHcIw5B4yx8DV_pl)e7cdad21-6b59-4f95-ba49-3627e86eae02.jpg"},{"url":"https://www.pornhub.com/photo/839055951","views":"782","rating":"100%","preview":"https://ei.phncdn.com/(m=bJaz0NV)(mh=BZSrX3QWKZf2gFlm)fbc512a5-5285-481c-9267-90925a508107.jpg"},{"url":"https://www.pornhub.com/photo/839055961","views":"963","rating":"100%","preview":"https://ei.phncdn.com/(m=bJaz0NV)(mh=mBS5GmZkBE_BjDoY)d370177d-505e-4b35-a0f8-cf8620dfee99.jpg"},{"url":"https://www.pornhub.com/photo/839055991","views":"633","rating":"86%","preview":"https://ei.phncdn.com/(m=bJaz0NV)(mh=qIBhYZiBBgKJD0F6)18188cb5-ae18-4a9d-97d7-63199f934c1c.jpg"},{"url":"https://www.pornhub.com/photo/839056001","views":"507","rating":"100%","preview":"https://ei.phncdn.com/(m=bJaz0NV)(mh=4Z4L6Dx90flv8Ldu)36c8a265-3e00-4874-91e5-6a4c5f4fa5bb.jpg"},{"url":"https://www.pornhub.com/photo/839056021","views":"906","rating":"100%","preview":"https://ei.phncdn.com/(m=bJaz0NV)(mh=JXLuMN35F2GSz7UE)8c53c70d-b4d8-4f6e-b113-a64dba454fae.jpg"},{"url":"https://www.pornhub.com/photo/839056101","views":"564","rating":"100%","preview":"https://ei.phncdn.com/(m=bJaz0NV)(mh=G5QBWnpvkUCcfCAm)7e5066bf-6d14-4c31-82ab-0db7ee32a30e.jpg"}],"provider":{"id":3874096,"username":"Eddie Lovett","url":"/model/eddie-lovett"},"tags":["threesome","amateur threesome","sharon white","elena lux","blonde","big butt","big boobs","fake tits","petite","two girls one guy","cumshot","cum on ass","tight pussy","big ass"]}