{"title":"Fingering Asshole & Black Shaved Pussy Fetish Closeup Babe Sheisnovember HD","photos":[{"url":"https://www.pornhub.com/photo/840609531","views":"474","rating":"100%","preview":"https://ei.phncdn.com/(m=bJaz0NV)(mh=HL_ymH_N5O6_OxuW)1cab1ed5-f9d4-4d9e-83dd-56e2cd9c1684.jpg"},{"url":"https://www.pornhub.com/photo/840609571","views":"558","rating":"100%","preview":"https://ei.phncdn.com/(m=bJaz0NV)(mh=_39uopms3mz0rDm9)fd307fdf-c5f7-435f-907a-079dd8ec097d.jpg"},{"url":"https://www.pornhub.com/photo/840609521","views":"353","rating":"100%","preview":"https://ei.phncdn.com/(m=bJaz0NV)(mh=Rbk5U_K5_rp_2ZxU)b06fada7-32fc-4e51-951d-87f5c90e5070.jpg"},{"url":"https://www.pornhub.com/photo/840609511","views":"326","rating":"100%","preview":"https://ei.phncdn.com/(m=bJaz0NV)(mh=nQykU68YTkZ4flO5)1bb911e4-30ac-4739-8828-23fd008e1766.jpg"},{"url":"https://www.pornhub.com/photo/840609391","views":"356","rating":"100%","preview":"https://ei.phncdn.com/(m=bJaz0NV)(mh=heiY8rsaFNDaD442)be2ea32a-7eca-4ef2-9716-c3a6672029db.jpg"},{"url":"https://www.pornhub.com/photo/840609441","views":"330","rating":"100%","preview":"https://ei.phncdn.com/(m=bJaz0NV)(mh=YXt7xVBQJtuPoMef)e9bf3cdf-89dc-4ce1-ac03-2302957c9eb1.jpg"},{"url":"https://www.pornhub.com/photo/840609491","views":"299","rating":"100%","preview":"https://ei.phncdn.com/(m=bJaz0NV)(mh=BsMH5WvmXDVNA5h3)9d2266aa-082b-43b9-a811-9d2bd7012faf.jpg"},{"url":"https://www.pornhub.com/photo/840609541","views":"254","rating":"100%","preview":"https://ei.phncdn.com/(m=bJaz0NV)(mh=n-OUfxXkE3Iagnog)de0fdfa2-3d05-4244-b0f9-36358820d5e8.jpg"},{"url":"https://www.pornhub.com/photo/840609471","views":"256","rating":"75%","preview":"https://ei.phncdn.com/(m=bJaz0NV)(mh=ZBF-KhU9pBuBKYpR)7cceb4d3-6d46-4e9d-a324-c22cbc800f45.jpg"},{"url":"https://www.pornhub.com/photo/840609501","views":"299","rating":"100%","preview":"https://ei.phncdn.com/(m=bJaz0NV)(mh=KmktVAUZOaxzUvZI)c9e72c66-13aa-4da3-9619-7d9de1e3d377.jpg"},{"url":"https://www.pornhub.com/photo/840609401","views":"251","rating":"0%","preview":"https://ei.phncdn.com/(m=bJaz0NV)(mh=MzPGBtDwRkIE7p2-)989b5ca7-1a66-4ea9-9bed-99312cd88f7e.jpg"},{"url":"https://www.pornhub.com/photo/840609411","views":"274","rating":"0%","preview":"https://ei.phncdn.com/(m=bJaz0NV)(mh=MWZHZQN_58I0AHYP)d4df78d0-c50c-4190-bb31-a22680085eac.jpg"},{"url":"https://www.pornhub.com/photo/840609581","views":"198","rating":"100%","preview":"https://ei.phncdn.com/(m=bJaz0NV)(mh=8NAxTfThIwMqNWO6)fc2ae9bd-8753-4348-9e13-0a9374107b70.jpg"},{"url":"https://www.pornhub.com/photo/840609431","views":"184","rating":"100%","preview":"https://ei.phncdn.com/(m=bJaz0NV)(mh=syC7QVyBp4ORzCHe)f97de0c2-d1c0-4dfe-ac26-77267f27c68c.jpg"},{"url":"https://www.pornhub.com/photo/840609421","views":"167","rating":"0%","preview":"https://ei.phncdn.com/(m=bJaz0NV)(mh=jyBsZ8P_aHkHYuAp)da8394c8-71f7-4f5e-83ec-ed7b18dcad2a.jpg"},{"url":"https://www.pornhub.com/photo/840609461","views":"144","rating":"100%","preview":"https://ei.phncdn.com/(m=bJaz0NV)(mh=_uZLzoER4TEqfqhS)a05417cf-9db3-4834-b002-bea570831d1e.jpg"},{"url":"https://www.pornhub.com/photo/840609481","views":"150","rating":"0%","preview":"https://ei.phncdn.com/(m=bJaz0NV)(mh=TRvbC0EI-yZ7ZPay)08d72dc6-6c22-4194-a954-51dfafb9c0f5.jpg"},{"url":"https://www.pornhub.com/photo/840609551","views":"482","rating":"100%","preview":"https://ei.phncdn.com/(m=bJaz0NV)(mh=vJf-2raGTHd4sP3W)2996bbd4-5bf7-4ab3-812d-a28aa9e3b057.jpg"},{"url":"https://www.pornhub.com/photo/840609451","views":"186","rating":"100%","preview":"https://ei.phncdn.com/(m=bJaz0NV)(mh=yxyaabFYfhhPg9Qy)47fc355f-391e-49fd-8334-3be6e724ce43.jpg"},{"url":"https://www.pornhub.com/photo/840609561","views":"212","rating":"100%","preview":"https://ei.phncdn.com/(m=bJaz0NV)(mh=JZ4xTL23EyAgyiUZ)7262ccdf-afbb-4202-b9b6-2ccfa6d48900.jpg"}],"provider":{"id":383684251,"username":"Sheisnovembercom","url":"/users/sheisnovembercom"},"tags":["msnovember","fingering","pussy fingering","asshole fingering","shaved pussy","fetish","closeup","black","ebony","asshole","stepdaughter","pornstar","anus","vagina","cute","big ass"]}