{"title":"The wife's smooth pussy","photos":[{"url":"https://www.pornhub.com/photo/837840841","views":"1.2K","rating":"100%","preview":"https://ei.phncdn.com/(m=bJaz0NV)(mh=98f64tHX8Gd2HZmv)6bbb6da7-9d21-4583-8b63-d3bfe5918bb6.jpg"},{"url":"https://www.pornhub.com/photo/837840851","views":"1.1K","rating":"94%","preview":"https://ei.phncdn.com/(m=bJaz0NV)(mh=gXhZGlGGYqhkYq5S)ef5c7b1d-c3f8-451c-ac77-d09fc31d6089.jpg"},{"url":"https://www.pornhub.com/photo/837840831","views":"983","rating":"93%","preview":"https://ei.phncdn.com/(m=bJaz0NV)(mh=NLgcVcuETs1p7hkV)37c804f9-1a1d-439b-af33-e488ec8e33c1.jpg"},{"url":"https://www.pornhub.com/photo/837840821","views":"935","rating":"100%","preview":"https://ei.phncdn.com/(m=bJaz0NV)(mh=sdoSrHt4Wa16HhwJ)45801dc9-d5f5-4bf5-a3d7-f1b9d79a6b86.jpg"}],"provider":{"id":2481742111,"username":"Husbandandwife8479","url":"/model/husbandandwife8479"},"tags":["bbw mom","wife","pussy","cunt","milf"]}